sigstore_protobuf_specs/__init__.py
sigstore_protobuf_specs/py.typed
sigstore_protobuf_specs/dev/__init__.py
sigstore_protobuf_specs/dev/sigstore/__init__.py
sigstore_protobuf_specs/dev/sigstore/bundle/__init__.py
sigstore_protobuf_specs/dev/sigstore/bundle/v1/__init__.py
sigstore_protobuf_specs/dev/sigstore/common/__init__.py
sigstore_protobuf_specs/dev/sigstore/common/v1/__init__.py
sigstore_protobuf_specs/dev/sigstore/events/__init__.py
sigstore_protobuf_specs/dev/sigstore/events/v1/__init__.py
sigstore_protobuf_specs/dev/sigstore/rekor/__init__.py
sigstore_protobuf_specs/dev/sigstore/rekor/v1/__init__.py
sigstore_protobuf_specs/dev/sigstore/rekor/v2/__init__.py
sigstore_protobuf_specs/dev/sigstore/trustroot/__init__.py
sigstore_protobuf_specs/dev/sigstore/trustroot/v1/__init__.py
sigstore_protobuf_specs/dev/sigstore/verification/__init__.py
sigstore_protobuf_specs/dev/sigstore/verification/v1/__init__.py
sigstore_protobuf_specs/google/__init__.py
sigstore_protobuf_specs/google/api/__init__.py
sigstore_protobuf_specs/io/__init__.py
sigstore_protobuf_specs/io/intoto/__init__.py
sigstore_protobuf_specs-0.5.0.dist-info/licenses/LICENSE
sigstore_protobuf_specs-0.5.0.dist-info/WHEEL
sigstore_protobuf_specs-0.5.0.dist-info/METADATA
sigstore_protobuf_specs-0.5.0.dist-info/RECORD
